hcpsdk/__init__.py
hcpsdk/version.py
hcpsdk/ips/__init__.py
hcpsdk/mapi/__init__.py
hcpsdk/namespace/__init__.py
hcpsdk/pathbuilder/__init__.py
hcpsdk-0.9.2.post5.dist-info/DESCRIPTION.rst
hcpsdk-0.9.2.post5.dist-info/METADATA
hcpsdk-0.9.2.post5.dist-info/metadata.json
hcpsdk-0.9.2.post5.dist-info/RECORD
hcpsdk-0.9.2.post5.dist-info/top_level.txt
hcpsdk-0.9.2.post5.dist-info/WHEEL
tests/__init__.py
tests/failtest.py
tests/idletimertest.py
tests/init_tests.py
tests/loadtest.py
tests/nsstatstest.py
tests/replicatest.py
tests/retrytest.py
tests/test_010_ips.py
tests/test_020_hcpsdk.py
tests/test_030_namespace.py
tests/test_040_mapi.py
tests/test_050_pathbuilder.py
tests/timeouttest.py
tests/trysdk.py
