Metadata-Version: 2.0
Name: hcpsdk
Version: 0.9.2.post5
Summary: An SDK for the Hitachi Content Platform (HCP)
Home-page: http://simont3.github.io/hcpsdk
Author: Thorsten Simons
Author-email: sw@snomis.de
License: MIT
Keywords: hcp sdk Hitachi Content Platform
Platform: UNKNOWN
Classifier: Development Status :: 5 - Production/Stable
Classifier: Intended Audience :: Developers
Classifier: Topic :: Software Development :: Libraries :: Python Modules
Classifier: Topic :: Internet :: WWW/HTTP :: Session
Classifier: License :: OSI Approved :: MIT License
Classifier: Programming Language :: Python :: 3.4
Classifier: Operating System :: OS Independent
Classifier: Natural Language :: English
Requires-Dist: dnspython3 (>=1.12.0)
Requires-Dist: alabaster (>=0.6.2)
